Workbook

Sheet Tablero
B6: ZONA | C6: DETALLE | D6: RACIONES DIA | G6: TOTAL PUNTOS DE BAJADA*
D7: COMIDAS | E7: REFRIGERIOS | G7: CAPITAL | H7: INTERIOR | J7: TOTAL DEPENDIENTES *
C8: ACCION SOCIAL * | D8: ='PADRON CAP'!H346 -> 13875 | E8: ='PADRON CAP'!I346 -> 11708 | G8: =SUMPRODUCT(1/COUNTIF('PADRON CAP'!D3:'PADRON CAP'!D342,'PADRON CAP'!D3:'PADRON CAP'!D342)) -> 212 | H8: =SUMPRODUCT(1/COUNTIF('PADRON INTERIOR'!B3:'PADRON INTERIOR'!B257,'PADRON INTERIOR'!B3:'PADRON INTERIOR'!B257)) -> 133 | J8: CAPITAL | K8: INTERIOR
C9: MINORIDAD Y FAMILIA * | D9: ='PADRON CAP'!H347 -> 1450 | E9: ='PADRON CAP'!I347 -> 1910 | G9: TOTAL | H9: =+G8+H8 -> 345 | J9: =SUMPRODUCT(1/COUNTIF('PADRON CAP'!D3:'PADRON CAP'!D342,'PADRON CAP'!D3:'PADRON CAP'!D342)) -> 212 | K9: =SUMPRODUCT(1/COUNTIF('PADRON INTERIOR'!C3:'PADRON INTERIOR'!C257,'PADRON INTERIOR'!C3:'PADRON INTERIOR'!C257)) -> 167
C10: MINISTERIO DE JUSTICIA * | D10: ='PADRON CAP'!H348 -> 410 | E10: ='PADRON CAP'!I348 -> 345 | J10: TOTAL | K10: =+J9+K9 -> 379
C11: ACCION SOCIAL * | D11: ='PADRON INTERIOR'!I261 -> 4615 | E11: ='PADRON INTERIOR'!J261 -> 7122
C12: MINORIDAD Y FAMILIA * | D12: ='PADRON INTERIOR'!I262 -> 2476 | E12: ='PADRON INTERIOR'!J262 -> 4805
C13: MINISTERIO DE JUSTICIA * | D13: ='PADRON INTERIOR'!I263 -> 85 | E13: ='PADRON INTERIOR'!J263 -> 145
B14: SUBTOTAL RAC. DIA PLAN 1 2026* | D14: =SUM(D8:D13) -> 22911 | E14: =SUM(E8:E13) -> 26035
C15: ASISTENCIA A LADRILLEROS | D15: ='PADRON CAP'!H349 -> 2365 | E15: ='PADRON CAP'!I349 -> 2250
C16: MOVIMIENTOS PASTORALES | D16: ='PADRON CAP'!H350 -> 0 | E16: ='PADRON CAP'!I350 -> 2400 | G16: CANTIDAD DE Centros de Distribución (Cabeceras) DE: | K16: CANTIDAD DE DEPENDIENTES (retiran de los puntos de distribución) por:
C17: MOVIMIENTOS SOCIALES | D17: ='PADRON CAP'!H351 -> 3950 | E17: ='PADRON CAP'!I351 -> 3153 | G17: ZONA | H17: REFRIGERIOS | I17: COMIDAS
B18: TOTAL RAC. DIA PLAN 1 2026 | D18: =+D14+D15+D16+D17 -> 29226 | E18: =+E14+E15+E16+E17 -> 33838 | G18: CAPITAL (1) | H18: {=SUM(--(FREQUENCY(IF('PADRON CAP'!I3:'PADRON CAP'!I342='PADRON CAP'!L1,MATCH('PADRON CAP'!D3:'PADRON CAP'!D342,'PADRON CAP'!D3:'PADRON CAP'!D342,0)),ROW('PADRON CAP'!D3:'PADRON CAP'!D342)-ROW('PADRON CAP'!D3)+1)>0))} -> 185 | I18: {=SUM(--(FREQUENCY(IF('PADRON CAP'!I3:'PADRON CAP'!I342='PADRON CAP'!M1,MATCH('PADRON CAP'!D3:'PADRON CAP'!D342,'PADRON CAP'!D3:'PADRON CAP'!D342,0)),ROW('PADRON CAP'!D3:'PADRON CAP'!D342)-ROW('PADRON CAP'!D3)+1)>0))} -> 155 | K18: ZONA | L18: REFRIGERIOS | M18: COMIDAS
G19: INTERIOR | H19: {=(SUM(--(FREQUENCY(IF('PADRON INTERIOR'!J3:'PADRON INTERIOR'!J257='PADRON INTERIOR'!M1,MATCH('PADRON INTERIOR'!B3:'PADRON INTERIOR'!B257,'PADRON INTERIOR'!B3:'PADRON INTERIOR'!B257,0)),ROW('PADRON INTERIOR'!B3:'PADRON INTERIOR'!B257)-ROW('PADRON INTERIOR'!B3)+1)>0)))} -> 119 | I19: {=SUM(--(FREQUENCY(IF('PADRON INTERIOR'!J3:'PADRON INTERIOR'!J257='PADRON INTERIOR'!N1,MATCH('PADRON INTERIOR'!B3:'PADRON INTERIOR'!B257,'PADRON INTERIOR'!B3:'PADRON INTERIOR'!B257,0)),ROW('PADRON INTERIOR'!B3:'PADRON INTERIOR'!B257)-ROW('PADRON INTERIOR'!B3)+1)>0))} -> 90 | K19: CAPITAL (1) | L19: =((COUNTIFS('PADRON CAP'!$I$3:$I$342,"REFRIGERIOS"))) -> 185 | M19: =((COUNTIFS('PADRON CAP'!$I$3:$I$2343,"comidas"))) -> 155
G20: TOTAL | H20: =+H18+H19 -> 304 | I20: =+I18+I19 -> 245 | K20: INTERIOR | L20: =(COUNTIFS('PADRON INTERIOR'!$J$3:$J$257,"REFRIGERIOS"))-'PADRON INTERIOR'!J273 -> 151 | M20: =(COUNTIFS('PADRON INTERIOR'!$J$3:$J$257,"COMIDAS"))-'PADRON INTERIOR'!I273 -> 104
K21: TOTAL | L21: =SUM(L19:L20) -> 336 | M21: =SUM(M19:M20) -> 259
D22: CAPITAL | E22: INTERIOR
C23: ACCION SOCIAL | D23: {=SUM(--(FREQUENCY(IF('PADRON CAP'!G3:'PADRON CAP'!G342='PADRON CAP'!D344,MATCH('PADRON CAP'!D3:'PADRON CAP'!D342,'PADRON CAP'!D3:'PADRON CAP'!D342,0)),ROW('PADRON CAP'!D3:'PADRON CAP'!D342)-ROW('PADRON CAP'!D3)+1)>0))} -> 153 | E23: 83
C24: MINORIDAD Y FAMILIA | D24: {=SUM(--(FREQUENCY(IF('PADRON CAP'!G3:'PADRON CAP'!G342='PADRON CAP'!D346,MATCH('PADRON CAP'!D3:'PADRON CAP'!D342,'PADRON CAP'!D4:'PADRON CAP'!D342,0)),ROW('PADRON CAP'!D3:'PADRON CAP'!D342)-ROW('PADRON CAP'!D3)+1)>0))} -> 25 | E24: 82
C25: MINSTERIO DE JUSTICIA | D25: {=SUM(--(FREQUENCY(IF('PADRON CAP'!G4:'PADRON CAP'!G343='PADRON CAP'!D349,MATCH('PADRON CAP'!D4:'PADRON CAP'!D343,'PADRON CAP'!D5:'PADRON CAP'!D343,0)),ROW('PADRON CAP'!D4:'PADRON CAP'!D343)-ROW('PADRON CAP'!D4)+1)>0))} -> 8 | E25: {=SUM(--(FREQUENCY(IF('PADRON INTERIOR'!I3:'PADRON INTERIOR'!I257='PADRON INTERIOR'!B261,MATCH('PADRON INTERIOR'!C3:'PADRON INTERIOR'!C257,'PADRON INTERIOR'!C3:'PADRON INTERIOR'!C257,0)),ROW('PADRON INTERIOR'!C3:'PADRON INTERIOR'!C257)-ROW('PADRON INTERIOR'!C3)+1)>0))} -> 3
C26: ASOC. LADRILLEROS (CAPITAL) | D26: {=SUM(--(FREQUENCY(IF('PADRON CAP'!G5:'PADRON CAP'!G344='PADRON CAP'!D345,MATCH('PADRON CAP'!D5:'PADRON CAP'!D344,'PADRON CAP'!D6:'PADRON CAP'!D344,0)),ROW('PADRON CAP'!D5:'PADRON CAP'!D344)-ROW('PADRON CAP'!D5)+1)>0))} -> 17
C27: MOVIMIENTOS PASTORALES | D27: {=SUM(--(FREQUENCY(IF('PADRON CAP'!G6:'PADRON CAP'!G345='PADRON CAP'!D347,MATCH('PADRON CAP'!D6:'PADRON CAP'!D345,'PADRON CAP'!D7:'PADRON CAP'!D345,0)),ROW('PADRON CAP'!D6:'PADRON CAP'!D345)-ROW('PADRON CAP'!D6)+1)>0))} -> 2
C28: MOVIMIENTOS SOCIALES | D28: {=SUM(--(FREQUENCY(IF('PADRON CAP'!G7:'PADRON CAP'!G346='PADRON CAP'!D348,MATCH('PADRON CAP'!D7:'PADRON CAP'!D346,'PADRON CAP'!D8:'PADRON CAP'!D346,0)),ROW('PADRON CAP'!D7:'PADRON CAP'!D346)-ROW('PADRON CAP'!D7)+1)>0))} -> 7
D29: =SUM(D23:D28) -> 212 | E29: =SUM(E23:E28) -> 168
D30: =+D29+E29 -> 380
D32: =+D33/D36 -> 0.77376823
C33: valor | D33: =+D18 -> 29226
C34: Plan | D34: =+D18 -> 29226 | H34: =+H35/H38 -> 0.89915765
C35: Saldo | D35: =+D36-D34 -> 8545 | G35: valor | H35: =+E18 -> 33838
C36: Licitado | D36: 37771 | G36: Plan | H36: =+E18 -> 33838
G37: Saldo | H37: =+H38-H36 -> 3795
C38: inicio | D38: =+D33-D39/1 -> 27726 | G38: Licitado | H38: 37633
C39: ancho | D39: 1500
C40: fin | D40: =SUM(D34:D36)-D38-D39 -> 46316 | G40: inicio | H40: =+H35-H41/1 -> 32338
G41: ancho | H41: 1500
G42: fin | H42: =SUM(H36:H38)-H40-H41 -> 41428
B52: Verano | C52: =(37771*42) -> 1586382 | D52: =26705*42 -> 1121610 | E52: =+D52/$C$60 -> 0.11783732 | F52: Verano | G52: =(37633*42) -> 1580586 | H52: =28578*42 -> 1200276 | I52: =+H52/$G$60 -> 0.12656445
B53: 1 | C53: =37771*30 -> 1133130 | D53: =29201*30 -> 876030 | E53: =+D53/$C$60+E52 -> 0.20987379 | F53: 1 | G53: =37633*30 -> 1128990 | H53: =33778*30 -> 1013340 | I53: =+H53/$G$60+I52 -> 0.23341723
B54: 2 | C54: =37771*30 -> 1133130 | D54: =29201*30 -> 876030 | E54: =+D54/$C$60+E53 -> 0.30191026 | F54: 2 | G54: =37633*30 -> 1128990 | H54: =33778*30 -> 1013340 | I54: =+H54/$G$60+I53 -> 0.34027
B55: 3 | C55: =37771*30 -> 1133130 | D55: =29201*30 -> 876030 | E55: =+D55/$C$60+E54 -> 0.39394673 | F55: 3 | G55: =37633*30 -> 1128990 | H55: =33778*30 -> 1013340 | I55: =+H55/$G$60+I54 -> 0.44712278
B56: 4 | C56: =37771*30 -> 1133130 | D56: =29201*30 -> 876030 | E56: =+D56/$C$60+E55 -> 0.4859832 | F56: 4 | G56: =37633*30 -> 1128990 | H56: =33778*30 -> 1013340 | I56: =+H56/$G$60+I55 -> 0.55397555
B57: 5 | C57: =37771*30 -> 1133130 | D57: =29201*30 -> 876030 | E57: =+D57/$C$60+E56 -> 0.57801967 | F57: 5 | G57: =37633*30 -> 1128990 | H57: =33778*30 -> 1013340 | I57: =+H57/$G$60+I56 -> 0.66082833
B58: 6 | C58: =37771*30 -> 1133130 | D58: =29201*30 -> 876030 | E58: =+D58/$C$60+E57 -> 0.67005614 | F58: 6 | G58: =37633*30 -> 1128990 | H58: =33778*30 -> 1013340 | I58: =+H58/$G$60+I57 -> 0.7676811
B59: 7 | C59: =37771*30 -> 1133130 | D59: =29201*30 -> 876030 | E59: =+D59/$C$60+E58 -> 0.76209261 | F59: 7 | G59: =37633*30 -> 1128990 | H59: =33778*30 -> 1013340 | I59: =+H59/$G$60+I58 -> 0.87453388
B60: total | C60: =SUM(C52:C59) -> 9518292 | D60: =SUM(D52:D59) -> 7253820 | F60: total | G60: =SUM(G52:G59) -> 9483516 | H60: =SUM(H52:H59) -> 8293656
G64: =SUM(G52:G60)-G63-G62 -> 18967032
B66: Grados | C66: =D66*PI() -> 0.65933795 | D66: =+E53 -> 0.20987379
C67: x | D67: y
B68: inicial | C68: 0 | D68: 0 | G68: Grados | H68: =I68*PI() -> 0.73330184 | I68: =+I53 -> 0.23341723
B69: final | C69: =COS(C66)*-1 -> -0.79039797 | D69: =SIN(C66) -> 0.6125937 | H69: x | I69: y
G70: inicial | H70: 0 | I70: 0
G71: final | H71: =COS(H68)*-1 -> -0.74296845 | I71: =SIN(H68) -> 0.66932644

Sheet Mapa
M4: DEPARTAMENTO | N4: ZONA | O4: Rac. Día Refrigerios (en %) | P4: Rac. Día Comidas (en %) | Q4: Cantidad de Dependientes (en %)*
M5: Capital | N5: CAPITAL | O5: 70.284834 | P5: 79.460775 | Q5: 0.60391198
M6: Dto. de Alvear | N6: C | O6: 0 | P6: 0 | Q6: 0.0024449878
M7: Dto. de Bella Vista | N7: B | O7: 0.97977465 | P7: 0.69275417 | Q7: 0.014669927
M8: Dto. de Berón de Astrada | N8: C | O8: 0 | P8: 0.11233851 | Q8: 0.0048899756
M9: Dto. de Concepción | N9: B | O9: 0.48988733 | P9: 0.74892342 | Q9: 0.014669927
M10: Dto. de Curuzú Cuatiá | N10: B | O10: 2.204493 | P10: 0.59913874 | Q10: 0.017114914
M11: Dto. de Empedrado | N11: A | O11: 0.96227868 | P11: 0.48680022 | Q11: 0.014669927
M12: Dto. de Esquina | N12: A | O12: 1.5396459 | P12: 0.11233851 | Q12: 0.02200489
M13: Dto. de Goya | N13: A | O13: 5.8961439 | P13: 4.9241715 | Q13: 0.035452323
M14: Dto. de General Paz | N14: B | O14: 0.49688572 | P14: 0.71147725 | Q14: 0.012224939
M15: Dto. de Itatí | N15: C | O15: 0.73483099 | P15: 1.5165699 | Q15: 0.0097799511
M16: Dto. de Ituzaingó | N16: C | O16: 1.417174 | P16: 0.99232353 | Q16: 0.02200489
... M29: Dto. de Sauce | N29: B | O29: 0.34991952 | P29: 0.093615428 | Q29: 0.0048899756
O30: =SUM(O5:O29) -> 100 | P30: =SUM(P5:P29) -> 100 | Q30: =SUM(Q5:Q29) -> 1
N35: capital | O35: =SUMIF($N$5:$N$29,"capital",$Q$5:$Q$29) -> 0.60391198
N36: a | O36: =SUMIF($N$5:$N$29,"A",$Q$5:$Q$29) -> 0.11246944
N37: b | O37: =SUMIF($N$5:$N$29,"b",$Q$5:$Q$29) -> 0.14669927
N38: c | O38: =SUMIF($N$5:$N$29,"c",$Q$5:$Q$29) -> 0.13447433

Sheet PADRON CAP
C1: PADRON PLAN 1 AÑO 2026 - DIRECCION DE SEGURIDAD ALIMENTARIA (MINISTERIO DE DESARROLLO SOCIAL PROVINCIA DE CORRIENTES) - CAPITAL | J1: REFRIGERIOS | K1: comidas | L1: REFRIGERIOS | M1: comidas
A2: Cód. CERES | B2: Denominación CERES | C2: ZONA | D2: COMEDORES Y MERENDEROS | E2: DOMICILIO | F2: RESPONSABLE | G2: TIPO RECEPTOR | H2: BENEF | I2: Servicio
A3: ACC-0023 | B3: 3 de Abril (Nº 79) | C3: CAPITAL | D3: 3 DE ABRIL | E3: Barrio 3 de Abril - Cabo de Horno 3900 | F3: Benitez, Cristina Mabel | G3: ACCION SOCIAL | H3: =290-10-20 -> 260 | I3: COMIDAS
A4: ACC-0128 | B4: R - Asociación Civil La Amistad | C4: CAPITAL | D4: Asociacion Civil la Amistad | E4: Bº VILLA RAQUEL140 Viviendas, MZAG, Casa 8 por Saavedra e/ Cadiz y Andalucia | F4: Barberan, Elizabet | G4: ACCION SOCIAL | H4: =300-20 -> 280 | I4: REFRIGERIOS
A5: ACC-0115 | B5: C - Asociación Civil Misioneros de la Esperanza | C5: CAPITAL | D5: Asociacion civil misioneros de la esperanza | E5: Los Atacamas 2465 - Corrientes Capital | F5: Estiveros, Sandra | G5: ACCION SOCIAL | H5: 30 | I5: REFRIGERIOS
A6: ACC-0081 | B6: Asociación Fotos del Alma (Nº 24) | C6: CAPITAL | D6: Asociacion Fotos del Alma | E6: Bº Ex Aero Club Sarmiento 2985 - Nº 24 | F6: JOKMANOVICH, ROSSANA | G6: ACCION SOCIAL | H6: 20 | I6: COMIDAS
A7: ACC-0081 | B7: Asociación Fotos del Alma (Nº 24) | C7: CAPITAL | D7: Asociacion Fotos del Alma | E7: Bº Ex Aero Club Sarmiento 2985 - Nº 24 | F7: JOKMANOVICH, ROSSANA | G7: ACCION SOCIAL | H7: 30 | I7: REFRIGERIOS
A8: ACC-0123 | B8: Y - Barrio Río Paraná (Sembrando Sueños) | C8: CAPITAL | D8: Bº Rio Parana (SEMBRANDO SUEÑOS) | E8: Bº Río Parana Mocoretá S/N | F8: Sánchez, Estela | G8: ACCION SOCIAL | H8: =75+20+20 -> 115 | I8: REFRIGERIOS
A9: ACC-0086 | B9: C. D. Bosco Domingo y Laura (Nº 45) | C9: CAPITAL | D9: C. D. BOSCO DOMINGO Y LAURA | E9: Av. IV Centenario 3400 (Mendoza al Sur) | F9: SERVETTI, JUAN RAMON | G9: ACCION SOCIAL | H9: 60 | I9: COMIDAS
A10: ACC-0086 | B10: C. D. Bosco Domingo y Laura (Nº 45) | C10: CAPITAL | D10: C. D. BOSCO DOMINGO Y LAURA | E10: Av. IV Centenario 3400 (Mendoza al Sur) | F10: SERVETTI, JUAN RAMON | G10: ACCION SOCIAL | H10: 100 | I10: REFRIGERIOS
A11: ACC-0033 | B11: C.C.I. Caridi (Nº 11) | C11: CAPITAL | D11: C.C.I. Caridi Nº 11 | E11: Bº CARIDI - Ibañez y Suipacha (Nº 2200) | F11: Miranda,Lidia Beatriz | G11: ACCION SOCIAL | H11: =120+40-20 -> 140 | I11: REFRIGERIOS
A12: ACC-0033 | B12: C.C.I. Caridi (Nº 11) | C12: CAPITAL | D12: C.C.I. Caridi Nº 11 | E12: Bº CARIDI - Ibañez y Suipacha (Nº 2200) | F12: Miranda,Lidia Beatriz | G12: ACCION SOCIAL | H12: =230-30 -> 200 | I12: COMIDAS
A13: ACC-0034 | B13: C.C.I. Hectorcito (Nº 35) | C13: CAPITAL | D13: C.C.I. Hectorcito | E13: Bº MOLINA PUNTA 136 VIV. LOTE 18 | F13: NUÑEZ, ANTONIA REGINA | G13: ACCION SOCIAL | H13: =140-10 -> 130 | I13: REFRIGERIOS
A14: ACC-0034 | B14: C.C.I. Hectorcito (Nº 35) | C14: CAPITAL | D14: C.C.I. Hectorcito | E14: Bº MOLINA PUNTA 136 VIV. LOTE 18 | F14: NUÑEZ, ANTONIA REGINA | G14: ACCION SOCIAL | H14: =160-20 -> 140 | I14: COMIDAS
A15: ACC-0037 | B15: C.C.I. María Eva y Juan Manuel (Nº 16) | C15: CAPITAL | D15: C.C.I. M. Eva y J. Manuel | E15: Bº Dr. MONTAÑA - Conte y Lara | F15: MONTIEL, MARIA | G15: ACCION SOCIAL | H15: =50+20+20 -> 90 | I15: REFRIGERIOS
A16: ACC-0037 | B16: C.C.I. María Eva y Juan Manuel (Nº 16) | C16: CAPITAL | D16: C.C.I. M. Eva y J. Manuel | E16: Bº Dr. MONTAÑA - Conte y Lara | F16: MONTIEL, MARIA | G16: ACCION SOCIAL | H16: =70+30+20+30 -> 150 | I16: COMIDAS
A17: ACC-0035 | B17: C.C.I. María Auxiliadora (Nº 18) | C17: CAPITAL | D17: C.C.I. María Auxiliadora | E17: Bº Galván - Piragini Niveyro y Av. 3 de Abril/ detrás del sap Bº Galvan II (Nº 18) | F17: LOPEZ, NORMA-TOLEDO, ALEJANDRO | G17: ACCION SOCIAL | H17: 110 | I17: REFRIGERIOS
A18: ACC-0035 | B18: C.C.I. María Auxiliadora (Nº 18) | C18: CAPITAL | D18: C.C.I. María Auxiliadora | E18: Bº Galván - Piragini Niveyro y Av. 3 de Abril/ detrás del sap Bº Galvan II (Nº 18) | F18: LOPEZ, NORMA-TOLEDO, ALEJANDRO | G18: ACCION SOCIAL | H18: 250 | I18: COMIDAS
A19: ACC-000032 | B19: C.C.I. Paranacito (Nº 53)(A) | C19: CAPITAL | D19: C.C.I. Paranacito | E19: Bº RIO PARANA ALTA GRACIA Y CABO DE HORNO - Nº 53 | F19: BERNIE, JOSE LUIS | G19: ACCION SOCIAL | H19: 180 | I19: REFRIGERIOS
A20: ACC-000032 | B20: C.C.I. Paranacito (Nº 53)(A) | C20: CAPITAL | D20: C.C.I. Paranacito | E20: Bº RIO PARANA ALTA GRACIA Y CABO DE HORNO - Nº 53 | F20: BERNIE, JOSE LUIS | G20: ACCION SOCIAL | H20: 260 | I20: COMIDAS
A21: ACC-0031 | B21: C.C.I. Santa Rita (Nº 01) | C21: CAPITAL | D21: C.C.I. Santa Rita (Nº 01) | E21: Bº Apipé, Colodrero y Sicilia | F21: BOGADO, ROSARIO | G21: ACCION SOCIAL | H21: =70+20-10 -> 80 | I21: REFRIGERIOS
A22: ACC-0031 | B22: C.C.I. Santa Rita (Nº 01) | C22: CAPITAL | D22: C.C.I. Santa Rita (Nº 01) | E22: Bº Apipé, Colodrero y Sicilia | F22: BOGADO, ROSARIO | G22: ACCION SOCIAL | H22: =120+20-10 -> 130 | I22: COMIDAS
A23: MDS_07202409 | B23: C.P.C. Paloma de la Paz | C23: CAPITAL | D23: C.P.C. Paloma de la Paz | E23: Bº Ongay - Valdepeña y Güemes | F23: Ferreyra, Karina | G23: ACCION SOCIAL | H23: 50 | I23: REFRIGERIOS
A24: ACC-0028 | B24: Cabo de Hornos (Nº 81) | C24: CAPITAL | D24: CABO DE HORNOS | E24: Bº BAÑADO SUR - Cabo de Hornos 4000 | F24: ALDERETE, PABLO ALFREDO | G24: ACCION SOCIAL | H24: 70 | I24: COMIDAS
A25: ACC-0046 | B25: Capilla Santa Marta (Nº 69) | C25: CAPITAL | D25: CAPILLA SANTA MARTA | E25: Bº SANTA MARTA -J.R. Vidal 4100 - Nº 69 | F25: ALEGRE, CLAUDIA DEL PILAR | G25: ACCION SOCIAL | H25: 160 | I25: COMIDAS
A26: ACC-0046 | B26: Capilla Santa Marta (Nº 69) | C26: CAPITAL | D26: CAPILLA SANTA MARTA | E26: Bº SANTA MARTA -J.R. Vidal 4100 - Nº 69 | F26: ALEGRE, CLAUDIA DEL PILAR | G26: ACCION SOCIAL | H26: 160 | I26: REFRIGERIOS
A27: MDS_ACC_2617 | B27: Capilla Guadalupe | C27: CAPITAL | D27: Capilla Guadalupe | E27: Los Tehuelches y Matacos - Bº San Antonio Oeste (Tunuyán 3376) | F27: Navarro, Tomasa | G27: ACCION SOCIAL | H27: 40 | I27: REFRIGERIOS
A28: SDH-CE-10 | B28: Capilla Roselo | C28: CAPITAL | D28: Capilla Roselo | E28: B° Quintana - Capital Nicaragua, Sta. Teresa de Calcuta y Suecia (Cel. 3794664602) | F28: Giménez, Florentino | G28: ACCION SOCIAL | H28: =80-20-30 -> 30 | I28: REFRIGERIOS
A29: ACC-0071 | B29: Capilla San Ignacio de Loyola (Nº 72) | C29: CAPITAL | D29: Capilla San Ignacio de Loyola (Nº 72) | E29: Bª LOMAS mza 6 lote 37 | F29: CERDAN, CELESTINA | G29: ACCION SOCIAL | H29: =100-20 -> 80 | I29: COMIDAS
A30: ACC-0067 | B30: Capilla San José (Nº 50) | C30: CAPITAL | D30: Capilla San José | E30: Bº QUINTA FERRE ZACARIAS SANCHEZ S/N - Nº 50 | F30: CORREA, ALFREDO SIMON | G30: ACCION SOCIAL | H30: 70 | I30: REFRIGERIOS
A31: ACC-0067 | B31: Capilla San José (Nº 50) | C31: CAPITAL | D31: Capilla San José | E31: Bº QUINTA FERRE ZACARIAS SANCHEZ S/N - Nº 50 | F31: CORREA, ALFREDO SIMON | G31: ACCION SOCIAL | H31: 180 | I31: COMIDAS
A32: ACC-0118 | B32: Z - Capilla Virgen de Itatí | C32: CAPITAL | D32: Capilla Virgen de Itati | E32: Bº ITATI Amado Bonpland Nº 395 Sec 3 Casa 32 | F32: Gómez, Oscar | G32: ACCION SOCIAL | H32: =180-20 -> 160 | I32: REFRIGERIOS
A33: ACC-0112 | B33: H - Capilla Virgen de Luján | C33: CAPITAL | D33: Capilla Virgen de Lujan | E33: Bª PONCE VIEJO - Vazquez esquina Moresi | F33: Gómez, María Mercedes. DNI: 20676211 | G33: ACCION SOCIAL | H33: 80 | I33: REFRIGERIOS
A34: ACC-0069 | B34: Capilla Virgen del Carmen (Nº 19) | C34: CAPITAL | D34: Capilla Virgen del Carmen (Nº 19) | E34: Bº GALVAN Alberdi 2979 - Nº 19 | F34: YEDRO, ELVA ITATI | G34: ACCION SOCIAL | H34: =120-20 -> 100 | I34: REFRIGERIOS
A35: ACC-0069 | B35: Capilla Virgen del Carmen (Nº 19) | C35: CAPITAL | D35: Capilla Virgen del Carmen (Nº 19) | E35: Bº GALVAN Alberdi 2979 - Nº 19 | F35: YEDRO, ELVA ITATI | G35: ACCION SOCIAL | H35: =200-20-20 -> 160 | I35: COMIDAS
A36: ACC -0050 | B36: Merendero "Carita de Ángel" | C36: CAPITAL | D36: Carita de Ángel | E36: Bº Virgen de los Dolores mza 2 casa 2 | F36: López Miranda, Ailin Melanie Milagros | G36: ACCION SOCIAL | H36: 50 | I36: REFRIGERIOS
A37: ACC-0049 | B37: Caritas Sucias (Nº 44) | C37: CAPITAL | D37: Caritas Sucias (Nº 44) | E37: Bº PLACIDO MARTINEZ - Bonpland sec E casa 22 | F37: VALLEJOS, RITA ISABEL | G37: ACCION SOCIAL | H37: =60+20-10 -> 70 | I37: COMIDAS
A38: ACC-0049 | B38: Caritas Sucias (Nº 44) | C38: CAPITAL | D38: Caritas Sucias (Nº 44) | E38: Bº PLACIDO MARTINEZ - Bonpland sec E casa 22 | F38: VALLEJOS, RITA ISABEL | G38: ACCION SOCIAL | H38: =130+20-20-10 -> 120 | I38: REFRIGERIOS
A39: ACC-0054 | B39: Centro Atención Personas Especiales (Nº 4 - CAPES SONUA) | C39: CAPITAL | D39: Centro At. Personas Esp.(CAPES SONUA) | E39: Bº BELGRANO Almte. Brown y EEUU Nº 4 | F39: Díaz, Leticia - Ramirez Mirta | G39: ACCION SOCIAL | H39: 100 | I39: REFRIGERIOS
A40: ACC-0054 | B40: Centro Atención Personas Especiales (Nº 4 - CAPES SONUA) | C40: CAPITAL | D40: Centro At. Personas Esp.(CAPES SONUA) | E40: Bº BELGRANO Almte. Brown y EEUU Nº 4 | F40: Díaz, Leticia - Ramirez Mirta | G40: ACCION SOCIAL | H40: 100 | I40: COMIDAS
A41: ACC-0048 | B41: Centro Comedor Santa Isabel (Nº 34) | C41: CAPITAL | D41: Centro Com. Santa Isabel | E41: Bº SANTA RITA calle Nº 1 Banda norte 2 cuadras y madia ruta Nº 5 | F41: LOPEZ, PEDRO - Gladys Araujo | G41: ACCION SOCIAL | H41: =160-10 -> 150 | I41: REFRIGERIOS
A42: ACC-0048 | B42: Centro Comedor Santa Isabel (Nº 34) | C42: CAPITAL | D42: Centro Com. Santa Isabel | E42: Bº SANTA RITA calle Nº 1 Banda norte 2 cuadras y madia ruta Nº 5 | F42: LOPEZ, PEDRO - Gladys Araujo | G42: ACCION SOCIAL | H42: =200-20 -> 180 | I42: COMIDAS
A43: ACC-0036 | B43: Centro Integral Cruz Roja (Nº 51) | C43: CAPITAL | D43: Centro Integral Cruz Roja | E43: Bº QUINTA FERRE Zacarías Sanchez 296 Nº 51 | F43: Claudia Beatriz Báez - Luis Vozza | G43: ACCION SOCIAL | H43: 110 | I43: REFRIGERIOS
A44: ACC-0036 | B44: Centro Integral Cruz Roja (Nº 51) | C44: CAPITAL | D44: Centro Integral Cruz Roja | E44: Bº QUINTA FERRE Zacarías Sanchez 296 Nº 51 | F44: Claudia Beatriz Báez - Luis Vozza | G44: ACCION SOCIAL | H44: 150 | I44: COMIDAS
A45: ACC-0099 | B45: G1 - Centro Misionero Pompeya | C45: CAPITAL | D45: Centro Misionero Pompeya | E45: Sgo. del Estero 353 (Capilla San Martín de Porres) | F45: Clara Adance - Mayal Maria del Carmen | G45: ACCION SOCIAL | H45: =90-10 -> 80 | I45: REFRIGERIOS
A46: ACC-0006 | B46: Centro Sol CIDECO (Nº 56) | C46: CAPITAL | D46: CIDECO | E46: Madariaga 288 | F46: Silva, Noelia Soledad | G46: ACCION SOCIAL | H46: =180+20+20+60 -> 280 | I46: COMIDAS
A47: ACC-0006 | B47: Centro Sol CIDECO (Nº 56) | C47: CAPITAL | D47: CIDECO | E47: Madariaga 288 | F47: Silva, Noelia Soledad | G47: ACCION SOCIAL | H47: =30+40 -> 70 | I47: REFRIGERIOS
A48: SDH-CE-13 | B48: Club Curupay 1 | C48: CAPITAL | D48: Club curupay 1 | E48: Vélez Sarfield y Sgo. del Estero | F48: Roa, Domingo | G48: ACCION SOCIAL | H48: =280-230+10+100 -> 160 | I48: REFRIGERIOS
A49: SDH-CE-14 | B49: Club Curupay 2 | C49: CAPITAL | D49: Club Curupay 2 | E49: Bº Arazati Gral Paz 70 | F49: Romero, Angel - Benita Catalina Ozuna | G49: ACCION SOCIAL | H49: =50+25 -> 75 | I49: REFRIGERIOS
A50: ACC-8128 | B50: Club Lipton | C50: CAPITAL | D50: Club Lipton | E50: Av. Alberdi 2267 | F50: Barrientos, Norma Beatríz | G50: ACCION SOCIAL | H50: 25 | I50: REFRIGERIOS
A51: ACC-0073 | B51: Hermana Cristina Rosa Mistica (Nº 75) | C51: CAPITAL | D51: Com. Hermana Cristina Rosa Mística | E51: Bº La Olla Avenida 200 y Calle Nueva Nº 75 | F51: VILLALBA, SUSANA DIONISIA | G51: ACCION SOCIAL | H51: =200+20+40-30+20+30 -> 280 | I51: REFRIGERIOS
A52: ACC-0073 | B52: Hermana Cristina Rosa Mistica (Nº 75) | C52: CAPITAL | D52: Com. Hermana Cristina Rosa Mística | E52: Bº La Olla Avenida 200 y Calle Nueva Nº 75 | F52: VILLALBA, SUSANA DIONISIA | G52: ACCION SOCIAL | H52: =200+20+20+30 -> 270 | I52: COMIDAS
A53: ACC-0020 | B53: Nuestra Señora de Lujan (Nº 46) | C53: CAPITAL | D53: Com. Nuestra Sra. De Luján | E53: Bº PONCE RUTA 5 km.1 calle Romulo Arturo Com. Nº 46 | F53: Marisa Beatriz Almirón | G53: ACCION SOCIAL | H53: =210-30-20 -> 160 | I53: REFRIGERIOS
A54: ACC-0020 | B54: Nuestra Señora de Lujan (Nº 46) | C54: CAPITAL | D54: Com. Nuestra Sra. De Luján | E54: Bº PONCE RUTA 5 km.1 calle Romulo Arturo Com. Nº 46 | F54: Marisa Beatriz Almirón | G54: ACCION SOCIAL | H54: =200-20-20 -> 160 | I54: COMIDAS
A55: ACC-0011 | B55: San Benito (Nº 55) | C55: CAPITAL | D55: Com. San Benito | E55: Bº SAN BENITO Entre Rios 2021 Nº 55 | F55: GILES, ISABEL | G55: ACCION SOCIAL | H55: 130 | I55: REFRIGERIOS
A56: ACC-0011 | B56: San Benito (Nº 55) | C56: CAPITAL | D56: Com. San Benito | E56: Bº SAN BENITO Entre Rios 2021 Nº 55 | F56: GILES, ISABEL | G56: ACCION SOCIAL | H56: =240-20+55 -> 275 | I56: COMIDAS
A57: MDS_07202401 | B57: Comedor Barriguita Feliz | C57: CAPITAL | D57: Comedor Barriguita Feliz | E57: Bº Sargento Cabral - Calle Irala Nº 2470 | F57: Rabez, Elcira Elizabet | G57: ACCION SOCIAL | H57: 30 | I57: REFRIGERIOS
A58: MDS_07202401 | B58: Comedor Barriguita Feliz | C58: CAPITAL | D58: Comedor Barriguita Feliz | E58: Bº Sargento Cabral - Calle Irala Nº 2470 | F58: Rabez, Elcira Elizabet | G58: ACCION SOCIAL | H58: 30 | I58: COMIDAS
A59: ACC-0056 | B59: San Miguel Arcangel (Nº 23) | C59: CAPITAL | D59: Comedor Ebenezer | E59: Bº Merceditas Collantes MZ 3 Casa 6 | F59: SANCHEZ, TERESITA MIRTA | G59: ACCION SOCIAL | H59: =210+20 -> 230 | I59: COMIDAS
A60: MDS_08012024 | B60: Comedor Fundación Animar | C60: CAPITAL | D60: Comedor Fundación Animar | E60: B° Cacique Canindeyú - Goya N° 19 | F60: Catougno, Analía | G60: ACCION SOCIAL | H60: 40 | I60: REFRIGERIOS
A61: MDS_08012024 | B61: Comedor Fundación Animar | C61: CAPITAL | D61: Comedor Fundación Animar | E61: B° Cacique Canindeyú - Goya N° 20 | F61: Catougno, Analía | G61: ACCION SOCIAL | H61: 40 | I61: COMIDAS
A62: MDS_07202402 | B62: Comedor Los Niños por una Sonrisa | C62: CAPITAL | D62: Comedor Los Niños por una Sonrisa | E62: Bº Galván II MZ F 3 Casa 15 | F62: Villafañe Yedro, Analía Natalia | G62: ACCION SOCIAL | H62: 30 | I62: REFRIGERIOS
A63: MDS_07202402 | B63: Comedor Los Niños por una Sonrisa | C63: CAPITAL | D63: Comedor Los Niños por una Sonrisa | E63: Bº Galván II MZ F 3 Casa 15 | F63: Villafañe Yedro, Analía Natalia | G63: ACCION SOCIAL | H63: 30 | I63: COMIDAS
A64: ACC_SOC_C | B64: Comedor Madre Maravilla | C64: CAPITAL | D64: Comedor Madre Maravilla | E64: Bº Quilmes, Hernandaria y Río Parana (DESCARGAR EN ALBERDI Nº 2792) | F64: Silva, Gladis | G64: ACCION SOCIAL | H64: =90+25 -> 115 | I64: COMIDAS
A65: ACC_SOC_C | B65: Comedor Madre Maravilla | C65: CAPITAL | D65: Comedor Madre Maravilla | E65: Bº Quilmes, Hernandaria y Río Parana (DESCARGAR EN ALBERDI Nº 2792) | F65: Silva, Gladis | G65: ACCION SOCIAL | H65: =90+25 -> 115 | I65: REFRIGERIOS
A66: MDS_0112025 | B66: Comedor Mi Refugio | C66: CAPITAL | D66: Comedor Mi Refugio | E66: B° Virgen de los dolores - Gutnisky N° 3040 | F66: Lugo, Estela Graciela | G66: ACCION SOCIAL | H66: 40 | I66: COMIDAS
A67: MDS_0112025 | B67: Comedor Mi Refugio | C67: CAPITAL | D67: Comedor Mi Refugio | E67: B° Virgen de los dolores - Gutnisky N° 3040 | F67: Lugo, Estela Graciela | G67: ACCION SOCIAL | H67: 40 | I67: REFRIGERIOS
A68: MDS_07202403 | B68: Comedor Neneco | C68: CAPITAL | D68: Comedor Neneco | E68: Pasaje Lujambio Nº 180 | F68: Romero, Alejandra Karina | G68: ACCION SOCIAL | H68: =145+100-205 -> 40 | I68: COMIDAS
A69: MDS_07202403 | B69: Comedor Neneco | C69: CAPITAL | D69: Comedor Neneco | E69: Pasaje Lujambio Nº 180 | F69: Romero, Alejandra Karina | G69: ACCION SOCIAL | H69: =200+82-252 -> 30 | I69: REFRIGERIOS
A70: ACC_SOC_C1 | B70: Comedor Ntra. Señora de Itati | C70: CAPITAL | D70: Comedor Ntra. Señora de Itatí | E70: PIZARRO 3400 | F70: Falcón, Gladis Itatí | G70: ACCION SOCIAL | H70: 40 | I70: COMIDAS
A71: ACC_SOC_C1 | B71: Comedor Ntra. Señora de Itati | C71: CAPITAL | D71: Comedor Ntra. Señora de Itatí | E71: PIZARRO 3400 | F71: Falcón, Gladis Itatí | G71: ACCION SOCIAL | H71: 40 | I71: REFRIGERIOS
A72: MDS_07202405 | B72: Comedor Pancita Feliz | C72: CAPITAL | D72: Comedor Pancita Feliz | E72: José María Rolón 2356 | F72: Pereyra, Norma Angéli | G72: ACCION SOCIAL | H72: 20 | I72: REFRIGERIOS
A73: MDS_07202405 | B73: Comedor Pancita Feliz | C73: CAPITAL | D73: Comedor Pancita Feliz | E73: José María Rolón 2356 | F73: Pereyra, Norma Angéli | G73: ACCION SOCIAL | H73: 20 | I73: COMIDAS
A74: ACC-0200 | B74: Comedor Pancita Llena | C74: CAPITAL | D74: Comedor Pancita Llena | E74: Bº Virgen de los Dolores. Mz. 4. Casa 3, Calle Cabeza de Vaca | F74: Villalba, Emilce | G74: ACCION SOCIAL | H74: 40 | I74: COMIDAS
A75: ACC-0200 | B75: Comedor Pancita Llena | C75: CAPITAL | D75: Comedor Pancita Llena | E75: Bº Virgen de los Dolores. Mz. 4. Casa 3, Calle Cabeza de Vaca | F75: Villalba, Emilce | G75: ACCION SOCIAL | H75: 40 | I75: REFRIGERIOS
A76: MDS_07202404 | B76: Comedor Papa Francisco | C76: CAPITAL | D76: Comedor Papa Francisco | E76: Bº Bañado Norte Calle Colombia 86, Mz 9 Lote | F76: Silva, Ramona | G76: ACCION SOCIAL | H76: 40 | I76: REFRIGERIOS
A77: MDS_07202404 | B77: Comedor Papa Francisco | C77: CAPITAL | D77: Comedor Papa Francisco | E77: Bº Bañado Norte Calle Colombia 86, Mz 9 Lote | F77: Silva, Ramona | G77: ACCION SOCIAL | H77: 40 | I77: COMIDAS
A78: MDS_07202406 | B78: Comedor Pequeño Milagro | C78: CAPITAL | D78: Comedor Pequeño Milagro | E78: Bº Bañado Sur, por calle Dr. Leloir MZ. 10 lote 16 | F78: Olegaria Orrego | G78: ACCION SOCIAL | H78: =240+90-290 -> 40 | I78: REFRIGERIOS
A79: MDS_07202406 | B79: Comedor Pequeño Milagro | C79: CAPITAL | D79: Comedor Pequeño Milagro | E79: Bº Bañado Sur, por calle Dr. Leloir MZ. 10 lote 17 | F79: Olegaria Orrego | G79: ACCION SOCIAL | H79: =175+25-160 -> 40 | I79: COMIDAS
A80: MDS_0122023 | B80: Comedor Rincón de Luz y Doña Beba | C80: CAPITAL | D80: Comedor Rincón de Luz y Doña Beba | E80: Barrio 3 de Abril MZ. D Casa Nº 17 Grupo 21 Viv | F80: Cinthia Capelli | G80: ACCION SOCIAL | H80: 40 | I80: COMIDAS
A81: MDS_0122023 | B81: Comedor Rincón de Luz y Doña Beba | C81: CAPITAL | D81: Comedor Rincón de Luz y Doña Beba | E81: Barrio 3 de Abril MZ. D Casa Nº 17 Grupo 21 Viv | F81: Cinthia Capelli | G81: ACCION SOCIAL | H81: 40 | I81: REFRIGERIOS
A82: ACC-0030 | B82: La Sagrada Familia II (Nº 30 - Mitaí Porá) | C82: CAPITAL | D82: Comedor Sagrada Familia II | E82: Bº 17 de AGOSTO 25 Viv. G2 Casa 22 Nº 30 Sagr. Flia. | F82: ACOSTA, DAVID SIXTO | G82: ACCION SOCIAL | H82: 80 | I82: REFRIGERIOS
A83: ACC-0030 | B83: La Sagrada Familia II (Nº 30 - Mitaí Porá) | C83: CAPITAL | D83: Comedor Sagrada Familia II | E83: Bº 17 de AGOSTO 25 Viv. G2 Casa 22 Nº 30 Sagr. Flia. | F83: ACOSTA, DAVID SIXTO | G83: ACCION SOCIAL | H83: 90 | I83: COMIDAS
A84: COM_ACC_Soc | B84: Comedor San Expedito | C84: CAPITAL | D84: Comedor San Expedito | E84: Bº ASENTAMIENTO PATONO I - FACUNDO QUIROGA 967 | F84: Maximiliano Morales | G84: ACCION SOCIAL | H84: =40+20+40+120 -> 220 | I84: REFRIGERIOS
A85: COM_ACC_Soc | B85: Comedor San Expedito | C85: CAPITAL | D85: Comedor San Expedito | E85: Bº ASENTAMIENTO PATONO I - FACUNDO QUIROGA 967 | F85: Maximiliano Morales | G85: ACCION SOCIAL | H85: =40+20+40+100 -> 200 | I85: COMIDAS
A86: MDS_07202407 | B86: Comedor San Martín de Porres | C86: CAPITAL | D86: Comedor San Martín de Porres | E86: Santiago del Estero Nº 353 esquina Juncal. | F86: Lencinas, Francisco | G86: ACCION SOCIAL | H86: 20 | I86: REFRIGERIOS
A87: MDS_07202407 | B87: Comedor San Martín de Porres | C87: CAPITAL | D87: Comedor San Martín de Porres | E87: Santiago del Estero Nº 353 esquina Juncal. | F87: Lencinas, Francisco | G87: ACCION SOCIAL | H87: 20 | I87: COMIDAS
A88: MDS_07202408 | B88: Comedor Santa Catalina | C88: CAPITAL | D88: Comedor Santa Catalina | E88: Bº Lomas del Mirador - Zaragoza al 599 | F88: Romero, Rogelio Ramón | G88: ACCION SOCIAL | H88: =230+70-260 -> 40 | I88: REFRIGERIOS
A89: MDS_07202408 | B89: Comedor Santa Catalina | C89: CAPITAL | D89: Comedor Santa Catalina | E89: Bº Lomas del Mirador - Zaragoza al 600 | F89: Romero, Rogelio Ramón | G89: ACCION SOCIAL | H89: =160-140 -> 20 | I89: COMIDAS
A90: ACC-0001 | B90: Santa Cecilia (Nº 17) | C90: CAPITAL | D90: Comedor Santa Cecilia | E90: Bº QUINTANA 142 viv Mz B Casa 8 Julio Verne y Renacimiento Nº 17 | F90: RAMIREZ, SILVIA VERÓNICA | G90: ACCION SOCIAL | H90: =200+25 -> 225 | I90: REFRIGERIOS
A91: ACC-0001 | B91: Santa Cecilia (Nº 17) | C91: CAPITAL | D91: Comedor Santa Cecilia | E91: Bº QUINTANA 142 viv Mz B Casa 8 Julio Verni y Renacimiento Nº 17 | F91: RAMIREZ, SILVIA VERÓNICA | G91: ACCION SOCIAL | H91: =250+45+30 -> 325 | I91: COMIDAS
A92: ACC_SOC_COM | B92: Comedor Santa Lucia I | C92: CAPITAL | D92: Comedor Santa Lucía | E92: Bº GALVÁN - RIO IGUAZÚ Y GARCILAZO DE LA VEGA (FRENTE DE LA DELEGACIÓN DEL BARRIO GALVÁN) | F92: VALLEJOS, ESTHER | G92: ACCION SOCIAL | H92: =40+20+10 -> 70 | I92: REFRIGERIOS
A93: ACC_SOC_COM | B93: Comedor Santa Lucia I | C93: CAPITAL | D93: Comedor Santa Lucía | E93: Bº GALVÁN - RIO IGUAZÚ Y GARCILAZO DE LA VEGA (FRENTE DE LA DELEGACIÓN DEL BARRIO GALVÁN) | F93: VALLEJOS, ESTHER | G93: ACCION SOCIAL | H93: =40+20+10 -> 70 | I93: COMIDAS
A94: NACC-16 | B94: Comedor Santa Lucia II | C94: CAPITAL | D94: Comedor Santa Lucía II | E94: Bº 17 de Agosto Sc. 9 Mza 53 Casa 16 (calle Sánchez de Bustamante) | F94: Benítez, Paola | G94: ACCION SOCIAL | H94: 60 | I94: REFRIGERIOS
A95: NACC-16 | B95: Comedor Santa Lucia II | C95: CAPITAL | D95: Comedor Santa Lucía II | E95: Bº 17 de Agosto Sc. 9 Mza 53 Casa 16 (calle Sánchez de Bustamante) | F95: Benítez, Paola | G95: ACCION SOCIAL | H95: 60 | I95: COMIDAS
A96: mds-2021-p7 | B96: Comedor Stella Maris | C96: CAPITAL | D96: Comedor Stella Maris | E96: Bº Colombia Granaderos Sector 1 Casa 23 Mz. D | F96: Mayol, Mirta | G96: ACCION SOCIAL | H96: 40 | I96: COMIDAS
A97: mds-2021-p7 | B97: Comedor Stella Maris | C97: CAPITAL | D97: Comedor Stella Maris | E97: Bº Colombia Granaderos Sector 1 Casa 23 Mz. D | F97: Mayol, Mirta | G97: ACCION SOCIAL | H97: 40 | I97: REFRIGERIOS
A98: MDS_08052024 | B98: Comedor y merendero "Sol" | C98: CAPITAL | D98: Comedor y merendero " Sol" | E98: Bº Arazaty - Gral Paz Nº 120 | F98: Sánchez, Romina Belén | G98: ACCION SOCIAL | H98: 50 | I98: COMIDAS
A99: MDS_08052024 | B99: Comedor y merendero "Sol" | C99: CAPITAL | D99: Comedor y merendero " Sol" | E99: Bº Arazaty - Gral Paz Nº 120 | F99: Sánchez, Romina Belén | G99: ACCION SOCIAL | H99: 50 | I99: REFRIGERIOS
A100: MDS_08022024 | B100: Comedor y merendero "Mamá Ata" | C100: CAPITAL | D100: Comedor y merendero "Mamá Ata" | E100: Bº Progreso - Matheu Nº 2738 | F100: López, Susana Elizabeth | G100: ACCION SOCIAL | H100: 30 | I100: COMIDAS
...

Sheet PADRON INTERIOR
A1: PADRON PLAN 1 AÑO 2026 - DIRECCION DE SEGURIDAD ALIMENTARIA (MINISTERIO DE DESARROLLO SOCIAL PROVINCIA DE CORRIENTES) - INTERIOR | M1: refrigerios | N1: comidas
A2: ZONA | B2: CENTRO DE DISTRIBUCIÓN | C2: CENTRO DE ENTREGA | D2: DIRECCIÓN | E2: TELEFONO | F2: DEPARTAMENTO | G2: LOCALIDAD | H2: BENEF | I2: ORGANISMO | J2: DETALLE SERV. | K2: st | L2: Org.II
A3: C | B3: C.P.F. Nº 1 San Jose Obrero | C3: C.P.F. Nº 1 San Jose Obrero | D3: Larrea y Suipacha | E3: Nora Ester Segovia (03772 401412) | F3: Dto. de Alvear | G3: Alvear | H3: 75 | I3: MIN. Y FLIA. | J3: REFRIGERIOS
A4: C | B4: C.P.F. Nº 1 San Jose Obrero | C4: C.P.F. Nº 1 San Jose Obrero | D4: Larrea y Suipacha | E4: Nora Ester Segovia (03772 401412) | F4: Dto. de Alvear | G4: Alvear | H4: 60 | I4: MIN. Y FLIA. | J4: COMIDAS
A5: A | B5: C.I.C. de la localidad de Bella Vista | C5: C.I.C. de la localidad de Bella Vista | D5: 25 de Mayo casi Charcas S/N | E5: 3777-543472 (Carolina Zalazar) | F5: Dto. de Bella Vista | G5: Bella Vista | H5: 100 | I5: ACCION SOCIAL | J5: COMIDAS
A6: A | B6: Gurisito Costero | C6: C.P.M. Nº 11 Gurisito Costero | D6: Belgrano y Costanera Zona Ribereña, El Carrizal | E6: 3777-554922 (Erika Carrasco) | F6: Dto. de Bella Vista | G6: Bella Vista | H6: 115 | I6: MIN. Y FLIA. | J6: COMIDAS
A7: A | B7: Gurisito Costero | C7: C.P.M. Nº 11 Gurisito Costero | D7: Belgrano y Costanera Zona Ribereña, El Carrizal | E7: 3777-554922 (Erika Carrasco) | F7: Dto. de Bella Vista | G7: Bella Vista | H7: 110 | I7: MIN. Y FLIA. | J7: REFRIGERIOS
A8: A | B8: Gurisito Costero | C8: Cong. Cristiana B. Vista | D8: Belgrano y Costanera Zona Ribereña, El Carrizal | E8: 3777-479009 (Graciela Lujan Gek) | F8: Dto. de Bella Vista | G8: Bella Vista | H8: 60 | I8: MIN. Y FLIA. | J8: COMIDAS
A9: A | B9: Gurisito Costero | C9: H.A. Nuevo Amanecer | D9: Estrada 66 - Bella Vista | E9: 3777-304595 (Soto Sandra Leticia) | F9: Dto. de Bella Vista | G9: Bella Vista | H9: 25 | I9: MIN. Y FLIA. | J9: COMIDAS
A10: A | B10: Gurisito Costero | C10: H.A. Nuevo Amanecer | D10: Estrada 66 - Bella Vista | E10: 3777-304595 (Soto Sandra Leticia) | F10: Dto. de Bella Vista | G10: Bella Vista | H10: 30 | I10: MIN. Y FLIA. | J10: REFRIGERIOS
A11: A | B11: Gurisito Costero | C11: J.M. Sagrado Corazón de Jesús | D11: Bº Los Pinos | E11: 3777-310761 (Fany Rolon) | F11: Dto. de Bella Vista | G11: Bella Vista | H11: 60 | I11: MIN. Y FLIA. | J11: COMIDAS
A12: A | B12: Gurisito Costero | C12: J.M. Sagrado Corazón de Jesús | D12: Bº Los Pinos | E12: 3777-310761 (Fany Rolon) | F12: Dto. de Bella Vista | G12: Bella Vista | H12: 90 | I12: MIN. Y FLIA. | J12: REFRIGERIOS
A13: A | B13: Liga Bellavistense de Fútbol (Para 8 Clubes) | C13: Liga Bellavistense de Fútbol (Para 8 Clubes) | D13: Sucre y Montevideo - Bella Vista | E13: 3777-609978 (Juan Insaurralde) | F13: Dto. de Bella Vista | G13: Bella Vista | H13: 250 | I13: ACCION SOCIAL | J13: REFRIGERIOS
A14: C | B14: C.P.M. Nº 22 Pago Redondo | C14: C.P.M. Nº 22 Pago Redondo | D14: Ex Mercado de Abasto | E14: 3794652143 (Celida Noemí Voulquin) | F14: Dto. de Berón de Astrada | G14: Berón de Astrada | H14: 35 | I14: MIN. Y FLIA. | J14: COMIDAS
... A18: A | B18: Fruto Verde | C18: Fruto Verde | D18: Riachuelo - 11 Leones (Zona Rural) | E18: 3794-273201 (Sandra Correa) | F18: Dto. de Capital | G18: Riachuelo | H18: 50 | I18: ACCION SOCIAL | J18: REFRIGERIOS
A19: A | B19: G - Los Chiquilines | C19: G - Los Chiquilines | D19: Riachuelo Pueblo Echazarreta 103 - Dpto. de Empedrado | E19: 3794-153881 (Lidia Esther Villan) | F19: Dto. de Capital | G19: Riachuelo | H19: =90+20+25 -> 135 | I19: ACCION SOCIAL | J19: COMIDAS
A20: A | B20: G - Los Chiquilines | C20: G - Los Chiquilines | D20: Riachuelo Pueblo Echazarreta 103 - Dpto. de Empedrado | E20: 3794-153881 (Lidia Esther Villan) | F20: Dto. de Capital | G20: Riachuelo | H20: =20+20 -> 40 | I20: ACCION SOCIAL | J20: REFRIGERIOS
A21: A | B21: Jesús Misericordioso (Nº 73) | C21: Jesús Misericordioso (Nº 73) | D21: Riachuelo - Rincón Roa Fopar | E21: 3794-631346 (Claudia Roa) | F21: Dto. de Capital | G21: Riachuelo | H21: 50 | I21: ACCION SOCIAL | J21: COMIDAS
A22: A | B22: Jesús Misericordioso (Nº 73) | C22: Jesús Misericordioso (Nº 73) | D22: Riachuelo - Rincón Roa Fopar | E22: 3794-631346 (Claudia Roa) | F22: Dto. de Capital | G22: Riachuelo | H22: 50 | I22: ACCION SOCIAL | J22: REFRIGERIOS
A23: A | B23: La Gurisada | C23: La Gurisada | D23: Km. 34 / Rta. 12 - El Sombrero (Empedrado) | E23: 3794-002572 (Graciela González) | F23: Dto. de Capital | G23: Riachuelo | H23: =130+20 -> 150 | I23: ACCION SOCIAL | J23: COMIDAS
A24: A | B24: La Gurisada | C24: La Gurisada | D24: Km. 34 / Rta. 12 - El Sombrero (Empedrado) | E24: 3794-002572 (Graciela González) | F24: Dto. de Capital | G24: Riachuelo | H24: 50 | I24: ACCION SOCIAL | J24: REFRIGERIOS
A25: A | B25: Riachuelo (Nº 76) | C25: Riachuelo (Nº 76) | D25: Riachuelo - 11 Leones / Cuarta Sección - Domínguez Marta D.N.I. Nº: 21.870.412. | E25: 3795-153281 (Marta Dominguez) | F25: Dto. de Capital | G25: Riachuelo | H25: 65 | I25: ACCION SOCIAL | J25: COMIDAS
A26: A | B26: Riachuelo (Nº 76) | C26: Riachuelo (Nº 76) | D26: Riachuelo - 11 Leones / Cuarta Sección - Domínguez Marta D.N.I. Nº: 21.870.412. | E26: 3795-153281 (Marta Dominguez) | F26: Dto. de Capital | G26: Riachuelo | H26: =65+20 -> 85 | I26: ACCION SOCIAL | J26: REFRIGERIOS
A27: A | B27: Santa Margarita | C27: Santa Margarita | D27: Riachuelo - Barrio Sta. Margarita, Los Lapachos | E27: 3794-566852 (Celia Beatriz Maidana) | F27: Dto. de Capital | G27: Riachuelo | H27: =50+25+45 -> 120 | I27: ACCION SOCIAL | J27: COMIDAS
A28: A | B28: Santa Margarita | C28: Santa Margarita | D28: Riachuelo - Barrio Sta. Margarita, Los Lapachos | E28: 3794-566852 (Celia Beatriz Maidana) | F28: Dto. de Capital | G28: Riachuelo | H28: =60+25+25 -> 110 | I28: ACCION SOCIAL | J28: REFRIGERIOS
A29: B | B29: Merendero Carita Feliz | C29: Merendero Carita Feliz | D29: Bº San Martín, bajar por Ruta Nac. 118 km 48 (2º Entrada a Tabay - Ermita de la Virgen de Luján - Galpones verdes de Coqui Palacio) Zunilda Palacio | E29: 3782-486684 (Zunilda Palacio ) | F29: Dto. de Concepción | G29: Tabay | H29: =20+20 -> 40 | I29: ACCION SOCIAL | J29: REFRIGERIOS
A30: B | B30: Merendero Rayo de Luz | C30: Merendero Rayo de Luz | D30: Ruta Nac. 118 km 49 (cerca Esc. Nº 211 - Adolfo Alvarez | E30: 3794-347342 (Andrea Edith Sanchez) | F30: Dto. de Concepción | G30: Tabay | H30: 50 | I30: ACCION SOCIAL | J30: REFRIGERIOS
A31: B | B31: Centro Nº 3 Virgen de Itatí | C31: Centro Nº 3 Virgen de Itatí | D31: Calle Curupy y San Martin- Colonia Tatacuá - (Cel. 3794075879 - Fernández) | E31: 3794-075879 (Carolina Fernández) | F31: Dto. de Concepción | G31: Concepción | H31: 150 | I31: MIN. Y FLIA. | J31: COMIDAS
A32: B | B32: J.M. Adela Feris de Romero | C32: J.M. Adela Feris de Romero | D32: Independencia 547 | E32: 3795-160547 (Ramona Mercedes Cardozo) | F32: Dto. de Concepción | G32: Concepción | H32: 45 | I32: MIN. Y FLIA. | J32: COMIDAS
A33: B | B33: J.M. Adela Feris de Romero | C33: J.M. Adela Feris de Romero | D33: Independencia 547 | E33: 3795-160547 (Ramona Mercedes Cardozo) | F33: Dto. de Concepción | G33: Concepción | H33: 40 | I33: MIN. Y FLIA. | J33: REFRIGERIOS
A34: B | B34: C.I.P.I. Nº 4 "Maria de Nazareth" | C34: C.I.P.I. Nº 4 "Maria de Nazareth" | D34: Detrás de la Intendencia de Santa Rosa | E34: 3794-204031 (Vanina Pavón) | F34: Dto. de Concepción | G34: Santa Rosa | H34: 45 | I34: MIN. Y FLIA. | J34: COMIDAS
A35: B | B35: C.I.P.I. Nº 4 "Maria de Nazareth" | C35: C.I.P.I. Nº 4 "Maria de Nazareth" | D35: Detrás de la Intendencia de Santa Rosa | E35: 3794-204031 (Vanina Pavón) | F35: Dto. de Concepción | G35: Santa Rosa | H35: 60 | I35: MIN. Y FLIA. | J35: REFRIGERIOS
A36: B | B36: Comedor Capilla San Cayetano | C36: Comedor Capilla San Cayetano | D36: Juan Bautista Cabral 045 | E36: 3782-525745 (Marcelo Otazo) - 3782-510835 (Lourdes Pereyra) | F36: Dto. de Concepción | G36: Santa Rosa | H36: 50 | I36: ACCION SOCIAL | J36: REFRIGERIOS
A37: B | B37: Comedor Capilla San Cayetano | C37: Comedor Capilla San Cayetano | D37: Juan Bautista Cabral 045 | E37: 3782-525745 (Marcelo Otazo) - 3782-510835 (Lourdes Pereyra) | F37: Dto. de Concepción | G37: Santa Rosa | H37: 50 | I37: ACCION SOCIAL | J37: COMIDAS
A38: B | B38: C.I.C. Curuzú Cuatiá | C38: C.I.C. Curuzú Cuatiá | D38: Sarmiento y Deán Funes | E38: 3774-630197 (Ana clara Jauregui) | F38: Dto. de Curuzú Cuatiá | G38: Curuzú Cuatiá | H38: 100 | I38: ACCION SOCIAL | J38: COMIDAS
A39: B | B39: C.I.C. Curuzú Cuatiá | C39: C.I.C. Curuzú Cuatiá | D39: Sarmiento y Deán Funes | E39: 3774-630197 (Ana clara Jauregui) | F39: Dto. de Curuzú Cuatiá | G39: Curuzú Cuatiá | H39: 270 | I39: ACCION SOCIAL | J39: REFRIGERIOS
A40: B | B40: Club Atlético Santa Rosa | C40: Club Atlético Santa Rosa | D40: Gral. Ramírez N° 832 | E40: 3774-402063 (Ariel Vallejos) | F40: Dto. de Curuzú Cuatiá | G40: Curuzú Cuatiá | H40: =60-30 -> 30 | I40: ACCION SOCIAL | J40: COMIDAS
A41: B | B41: Club Atlético Santa Rosa | C41: Club Atlético Santa Rosa | D41: Gral. Ramírez N° 832 | E41: 3774-402063 (Ariel Vallejos) | F41: Dto. de Curuzú Cuatiá | G41: Curuzú Cuatiá | H41: =150-20 -> 130 | I41: ACCION SOCIAL | J41: REFRIGERIOS
A42: B | B42: H.A. Adelina B. de Ezcurra | C42: H.A. Adelina B. de Ezcurra | D42: Av. España 244 | E42: 3774-465885 (Carmen Marticorena) | F42: Dto. de Curuzú Cuatiá | G42: Curuzú Cuatiá | H42: 30 | I42: MIN. Y FLIA. | J42: COMIDAS
A43: B | B43: H.A. Adelina B. de Ezcurra | C43: H.A. Adelina B. de Ezcurra | D43: Av. España 244 | E43: 3774-465885 (Carmen Marticorena) | F43: Dto. de Curuzú Cuatiá | G43: Curuzú Cuatiá | H43: =70 -> 70 | I43: MIN. Y FLIA. | J43: REFRIGERIOS
A44: B | B44: J.M. Mitaí Porá | C44: J.M. Mitaí Porá | D44: Barrio 200 Viv. - Entre 16 de Noviembre e Isabel La Católica | E44: 3774-465021 (Amalia Andrea Silva) | F44: Dto. de Curuzú Cuatiá | G44: Curuzú Cuatiá | H44: 80 | I44: MIN. Y FLIA. | J44: COMIDAS
A45: B | B45: J.M. Mitaí Porá | C45: J.M. Mitaí Porá | D45: Barrio 200 Viv. - Entre 16 de Noviembre e Isabel La Católica | E45: 3774-465021 (Amalia Andrea Silva) | F45: Dto. de Curuzú Cuatiá | G45: Curuzú Cuatiá | H45: 80 | I45: MIN. Y FLIA. | J45: REFRIGERIOS
A46: B | B46: J.M. Semillitas | C46: J.M. Semillitas | D46: Gobernador Gómez 835 (detrás de la Terminal) | E46: 3794-722934 (Martinez Silvia Noemi) | F46: Dto. de Curuzú Cuatiá | G46: Curuzú Cuatiá | H46: 85 | I46: MIN. Y FLIA. | J46: COMIDAS
A47: B | B47: J.M. Semillitas | C47: J.M. Semillitas | D47: Gobernador Gómez 835 (detrás de la Terminal) | E47: 3794-722934 (Martinez Silvia Noemi) | F47: Dto. de Curuzú Cuatiá | G47: Curuzú Cuatiá | H47: 90 | I47: MIN. Y FLIA. | J47: REFRIGERIOS
A48: B | B48: Liga de Fútbol Gral. Belgrano | C48: Liga de Fútbol Gral. Belgrano | D48: Gral. Ramírez N° 753 - Sr Ojeda | E48: 3774-634021 (Daniel Ojeda) | F48: Dto. de Curuzú Cuatiá | G48: Curuzú Cuatiá | H48: 120 | I48: ACCION SOCIAL | J48: REFRIGERIOS
A49: B | B49: Delegación Desarrollo Social de Perugorría | C49: Delegación Desarrollo Social de Perugorría | D49: Pedro Nolasco S/N | E49: 3777-415719 (Eliana Gimena López) | F49: Dto. de Curuzú Cuatiá | G49: Perugorría | H49: =20+20 -> 40 | I49: ACCION SOCIAL | J49: REFRIGERIOS
A50: A | B50: Comedor Manuel Derqui | C50: Comedor Manuel Derqui | D50: RUTA PROV. 35 | E50: 3794-923704 (Catalina Cáceres) | F50: Dto. de Empedrado | G50: Derqui | H50: 40 | I50: ACCION SOCIAL | J50: REFRIGERIOS
A51: A | B51: Comedor Manuel Derqui | C51: Comedor Manuel Derqui | D51: RUTA PROV. 35 | E51: 3794-923704 (Catalina Cáceres) | F51: Dto. de Empedrado | G51: Derqui | H51: 40 | I51: ACCION SOCIAL | J51: COMIDAS
A52: A | B52: Asoc. de Malloneros San Expedito | C52: Asoc. de Malloneros San Expedito (Tomasa Franco) | D52: Belgrano 750 | E52: 3794-027649 (Tomasa Franco) | F52: Dto. de Empedrado | G52: Empedrado | H52: =25+20+15 -> 60 | I52: ACCION SOCIAL | J52: COMIDAS
A53: A | B53: Asoc. de Malloneros San Expedito | C53: Asoc. de Malloneros San Expedito (Tomasa Franco) | D53: Belgrano 750 | E53: 3794-027649 (Tomasa Franco) | F53: Dto. de Empedrado | G53: Empedrado | H53: =25+20+15 -> 60 | I53: ACCION SOCIAL | J53: REFRIGERIOS
A54: A | B54: C.P.M. Nº 19 Niños Felices Anexo CIPI N° 6 Perlita | C54: C.P.M. Nº 19 Niños Felices Anexo CIPI N° 6 Perlita | D54: Belgrano 1960 | E54: 3794-037428 (Mónica Ortiz) | F54: Dto. de Empedrado | G54: Empedrado | H54: 90 | I54: MIN. Y FLIA. | J54: REFRIGERIOS
A55: A | B55: Cañada Quiróz II - Gruta de la Virgen | C55: Cañada Quiróz II - Gruta de la Virgen | D55: Av. Alejo Rueda - Gruta de la Virgen | E55: Estela Godoy (3794080941) | F55: Dto. de Empedrado | G55: Empedrado | H55: 60 | I55: ACCION SOCIAL | J55: REFRIGERIOS
A56: A | B56: H.A. Teresa Faraone | C56: H.A. Teresa Faraone | D56: Alsina y 9 de Julio | E56: 3795-063413 (Teresa Coronel) | F56: Dto. de Empedrado | G56: Empedrado | H56: 30 | I56: MIN. Y FLIA. | J56: COMIDAS
A57: A | B57: H.A. Teresa Faraone | C57: H.A. Teresa Faraone | D57: Alsina y 9 de Julio | E57: 3795-063413 (Teresa Coronel) | F57: Dto. de Empedrado | G57: Empedrado | H57: 75 | I57: MIN. Y FLIA. | J57: REFRIGERIOS
A58: A | B58: Iglesia Asamblea de Dios-Templo Filadelfia | C58: Iglesia Asamblea de Dios-Templo Filadelfia | D58: Santiago del Estero 710 | E58: 3782-431769 (Lidia Leañez) | F58: Dto. de Empedrado | G58: Empedrado | H58: 40 | I58: ACCION SOCIAL | J58: REFRIGERIOS
A59: A | B59: C.P.M. Nº 32 "Santa Rita" | C59: C.P.M. Nº 32 "Santa Rita" | D59: Barrio San Fernando - Los Ceibos S/N | E59: 3777-611906 (Ana Isabel Rojo) | F59: Dto. de Esquina | G59: Esquina | H59: 65 | I59: MIN. Y FLIA. | J59: REFRIGERIOS
A60: A | B60: C.P.M. Nº 5 "Niño Jesús" | C60: C.P.M. Nº 5 "Niño Jesús" | D60: Bº Mancini - Los Sauces 1920 (detrás de la cancha San Martin) | E60: 3777-305306 (Lucrecia Martinez) | F60: Dto. de Esquina | G60: Esquina | H60: 40 | I60: MIN. Y FLIA. | J60: REFRIGERIOS
A61: A | B61: Centro de Día "Solcito" | C61: Centro de Día "Solcito" | D61: Marcelino Dávila S/N (entre Rta. 12 y los Ceibos) | E61: 3777-284428 (Jennifer Borda) | F61: Dto. de Esquina | G61: Esquina | H61: 60 | I61: MIN. Y FLIA. | J61: REFRIGERIOS
A62: A | B62: Centro Obispo "Alberto Devoto" (Esquina) | C62: Centro Obispo "Alberto Devoto" (Esquina) | D62: B° San Antonio - Noain Ortigóza S/N (al lado de la Capilla San Antonio) | E62: 3777-312095 (Ariel Grenat) | F62: Dto. de Esquina | G62: Esquina | H62: 100 | I62: MIN. Y FLIA. | J62: REFRIGERIOS
A63: A | B63: H.A. San Vicente de Paul (Esquina) | C63: H.A. San Vicente de Paul (Esquina) | D63: Gbdor. Velazco 687 | E63: 3777-283833 (Silvia Ojeda) | F63: Dto. de Esquina | G63: Esquina | H63: 30 | I63: MIN. Y FLIA. | J63: COMIDAS
A64: A | B64: H.A. San Vicente de Paul (Esquina) | C64: H.A. San Vicente de Paul (Esquina) | D64: Gbdor. Velazco 687 | E64: 3778-283833 (Silvia Ojeda) | F64: Dto. de Esquina | G64: Esquina | H64: 60 | I64: MIN. Y FLIA. | J64: REFRIGERIOS
A65: A | B65: J.M. El Carmen | C65: J.M. El Carmen | D65: Serrano Soto 66 | E65: 3777-207724 (Nancy Martinez) | F65: Dto. de Esquina | G65: Esquina | H65: 50 | I65: MIN. Y FLIA. | J65: REFRIGERIOS
... A74: C | B74: Club Rana Itá Ibaté | C74: Club Rana Itá Ibaté | D74: Berón de Astrada entre 9 de julio y Alberdi | E74: 378-1412983 (José Luis Rodriguez) | F74: Dto. de General Paz | G74: Itá Ibaté | H74: 32 | I74: ACCION SOCIAL | J74: REFRIGERIOS
A75: C | B75: Corazón Contento de Arenruguá | C75: Corazón Contento de Arenruguá | D75: Alberdi e/ Ituzaingó y Paraguay (Itá Ibaté) | E75: 3794-922748 (Esther Bramante) | F75: Dto. de General Paz | G75: Itá Ibaté | H75: =25+20+25 -> 70 | I75: ACCION SOCIAL | J75: REFRIGERIOS
A76: C | B76: Corazón Contento de Arenruguá | C76: Corazón Contento de Arenruguá | D76: Alberdi e/ Ituzaingó y Paraguay (Itá Ibaté) | E76: 3794-922748 (Esther Bramante) | F76: Dto. de General Paz | G76: Itá Ibaté | H76: =25+20+25 -> 70 | I76: ACCION SOCIAL | J76: COMIDAS
A77: A | B77: Centro de Día "Días Felices" | C77: Albergue Juvenil Hogar Rural | D77: Mariano I. Loza S/N - Goya | E77: 3777-621686 (Raimundi Gladis) | F77: Dto. de Goya | G77: Goya | H77: 80 | I77: MIN. Y FLIA. | J77: COMIDAS
A78: A | B78: Centro de Día "Días Felices" | C78: Albergue Juvenil Hogar Rural | D78: Mariano I. Loza S/N - Goya | E78: 3777-621686 (Raimundi Gladis) | F78: Dto. de Goya | G78: Goya | H78: 90 | I78: MIN. Y FLIA. | J78: REFRIGERIOS
A79: A | B79: Centro de Día "Días Felices" | C79: C.P.M. Nº 25 "Arco Iris" | D79: Barrio Sarmiento - Goya | E79: 3777-400944 (Elizabeth Ayala) | F79: Dto. de Goya | G79: Goya | H79: 80 | I79: MIN. Y FLIA. | J79: REFRIGERIOS
A80: A | B80: Centro de Día "Días Felices" | C80: C.P.M. Nº 29 "Chamiguitos" | D80: Barrio Costas Las Rosas - Goya | E80: 3777-558050 (Melina Belén Tones) | F80: Dto. de Goya | G80: Goya | H80: 70 | I80: MIN. Y FLIA. | J80: REFRIGERIOS
A81: A | B81: Centro de Día "Días Felices" | C81: Centro de Día "Días Felices" | D81: Av. España 875 - Goya | E81: 3777-538746 (María Maciel) | F81: Dto. de Goya | G81: Goya | H81: 40 | I81: MIN. Y FLIA. | J81: REFRIGERIOS
A82: A | B82: Centro de Día "Días Felices" | C82: H.N. San Vicente de Paul | D82: Sargento Cabral 351 - Goya | E82: 3777-633284 (Julieta Gómez Muñoz) | F82: Dto. de Goya | G82: Goya | H82: 45 | I82: Mtrio. de Justicia | J82: COMIDAS
A83: A | B83: Centro de Día "Días Felices" | C83: H.N. San Vicente de Paul | D83: Sargento Cabral 351 - Goya | E83: 3777-633284 (Julieta Gómez Muñoz) | F83: Dto. de Goya | G83: Goya | H83: 50 | I83: Mtrio. de Justicia | J83: REFRIGERIOS
A84: A | B84: Centro de Día "Días Felices" | C84: Instituto de Orientación Juvenil | D84: Km. 6, Frente al Aeropuerto | E84: 3794-597128 (Analia Segovia) | F84: Dto. de Goya | G84: Goya | H84: 20 | I84: MIN. Y FLIA. | J84: COMIDAS
A85: A | B85: Centro de Día "Días Felices" | C85: Instituto de Orientación Juvenil | D85: Km. 6, Frente al Aeropuerto | E85: 3794-597128 (Analia Segovia) | F85: Dto. de Goya | G85: Goya | H85: 30 | I85: MIN. Y FLIA. | J85: REFRIGERIOS
A86: A | B86: Centro de Día "Días Felices" | C86: J.M. "Abuelo Justo" | D86: Barrio 432 Viviendas | E86: 3777648938 (Laura Medina) | F86: Dto. de Goya | G86: Goya | H86: 90 | I86: MIN. Y FLIA. | J86: REFRIGERIOS
A87: A | B87: Centro de Día "Días Felices" | C87: J.M. "Mamá Perla" | D87: Piragine Niveyro 730 - Goya | E87: 3777624146 (Belen Balestra) | F87: Dto. de Goya | G87: Goya | H87: 100 | I87: MIN. Y FLIA. | J87: REFRIGERIOS
A88: A | B88: Delegación Desarrollo Social (Goya) | C88: Comedor San Cayetano | D88: Tucumán y Pujol | E88: 3777-637016 (Beatriz Lopez) | F88: Dto. de Goya | G88: Goya | H88: 100 | I88: ACCION SOCIAL | J88: COMIDAS
... A97: A | B97: H.A. San José | C97: H.A. San José | D97: Sargento Cabral 351 - Goya | E97: 3777-221962 (María Raquel Ortiz) | F97: Dto. de Goya | G97: Goya | H97: 60 | I97: MIN. Y FLIA. | J97: REFRIGERIOS
A98: A | B98: Movimiento Libre del Sur (Goya) | C98: Movimiento Libre del Sur | D98: Barrio Belgrano Mz G Casa 1 | E98: Ocampo, Miriam Matilde (Cel.11-2338-9298) | F98: Dto. de Goya | G98: Goya | H98: =30+20 -> 50 | I98: ACCION SOCIAL | J98: COMIDAS
A99: C | B99: Basílica de Itatí (ITATI) | C99: Basilica de Itatí | D99: Monseñor Luis Niella 340 | E99: 11-3436-0047 (Porfirio Ramirez) | F99: Dto. de Itatí | G99: Itatí | H99: 30 | I99: ACCION SOCIAL | J99: REFRIGERIOS
A100: C | B100: Basílica de Itatí (ITATI) | C100: Basilica de Itatí | D100: Monseñor Luis Niella 340 | E100: 11-3436-0047 (Porfirio Ramirez) | F100: Dto. de Itatí | G100: Itatí | H100: 60 | I100: ACCION SOCIAL | J100: COMIDAS
A101: C | B101: C.I.C. Dr. René Favaloro | C101: C.I.C. Dr. René Favaloro | D101: Bº Avá Rapé e/ Villegas y 7 de Diciembre - Norberto Ramírez | E101: 3794121156 (Mirian Lugo) | F101: Dto. de Itatí | G101: Itatí | H101: =180+60+60 -> 300 | I101: ACCION SOCIAL | J101: COMIDAS
A102: C | B102: C.I.C. Dr. René Favaloro | C102: C.I.C. Dr. René Favaloro | D102: Bº Avá Rapé e/ Villegas y 7 de Diciembre - Norberto Ramírez | E102: 3794121156 (Mirian Lugo) | F102: Dto. de Itatí | G102: Itatí | H102: 100 | I102: ACCION SOCIAL | J102: REFRIGERIOS
A103: C | B103: C.P.M. Nº 3 "Cambacito" | C103: C.P.M. Nº 3 "Cambacito" | D103: 25 de Mayo S/N (Al lado de Estación Terminal) | E103: 3795-330487 (Cynthya Elisabet Umbert) | F103: Dto. de Itatí | G103: Itatí | H103: 35 | I103: MIN. Y FLIA. | J103: REFRIGERIOS
A104: C | B104: Comedor Nueva Esperanza (ITATI) | C104: Comedor Nueva Esperanza | D104: 25 de Mayo 480. Analía Ramírez | E104: 3795-164878 (Darío González) | F104: Dto. de Itatí | G104: Itatí | H104: =25+20 -> 45 | I104: ACCION SOCIAL | J104: COMIDAS
A105: C | B105: Comedor Nueva Esperanza (ITATI) | C105: Comedor Nueva Esperanza | D105: 25 de Mayo 480. Analía Ramírez | E105: 3795-164878 (Darío González) | F105: Dto. de Itatí | G105: Itatí | H105: =25+15+40 -> 80 | I105: ACCION SOCIAL | J105: REFRIGERIOS
A106: C | B106: ONG RED MUNDIAL | C106: ONG RED MUNDIAL | D106: Bº Entel - Alberdi s/n - Casa Nº 8 e/ Pedro Mola y 9 de Julio | E106: 3758-403089 (Marta Ifran) | F106: Dto. de Ituzaingó | G106: San Carlos | H106: 20 | I106: ACCION SOCIAL | J106: REFRIGERIOS
A107: C | B107: ONG RED MUNDIAL | C107: ONG RED MUNDIAL | D107: Bº Entel - Alberdi s/n - Casa Nº 8 e/ Pedro Mola y 9 de Julio | E107: 3758-403089 (Marta Ifran) | F107: Dto. de Ituzaingó | G107: San Carlos | H107: 20 | I107: ACCION SOCIAL | J107: COMIDAS
A108: C | B108: Asociación Hogar de Niños Filadelfia | C108: Asociación Hogar de Niños Filadelfia | D108: Ruta 12 km 1275 Luis Alberto Santibañez | E108: 3786-458870 (Irma Esther Marzoratti) | F108: Dto. de Ituzaingó | G108: Ituzaingó | H108: =30+30 -> 60 | I108: ACCION SOCIAL | J108: COMIDAS
A109: C | B109: Asociación Hogar de Niños Filadelfia | C109: Asociación Hogar de Niños Filadelfia | D109: Ruta 12 km 1275 Luis Alberto Santibañez | E109: 3786-458870 (Irma Esther Marzoratti) | F109: Dto. de Ituzaingó | G109: Ituzaingó | H109: =30+60 -> 90 | I109: ACCION SOCIAL | J109: REFRIGERIOS
A110: C | B110: CADI ITUZAINGÓ | C110: CADI ITUZAINGÓ | D110: CALLE M 14 B° MIL VIV. | E110: 3786-451076 (Natalia Malavé) | F110: Dto. de Ituzaingó | G110: Ituzaingó | H110: =40 -> 40 | I110: ACCION SOCIAL | J110: REFRIGERIOS
A111: C | B111: Comedor Denis Ituzaingo | C111: Comedor Denis Ituzaingo | D111: Bº Paraná - Calle Madariaga y Mendoza. | E111: 3786-511681 (Silvia Belarde) | F111: Dto. de Ituzaingó | G111: Ituzaingó | H111: 40 | I111: ACCION SOCIAL | J111: COMIDAS
A112: C | B112: Comedor Denis Ituzaingo | C112: Comedor Denis Ituzaingo | D112: Bº Paraná - Calle Madariaga y Mendoza. | E112: 3786-511681 (Silvia Belarde) | F112: Dto. de Ituzaingó | G112: Ituzaingó | H112: 40 | I112: ACCION SOCIAL | J112: REFRIGERIOS
A113: C | B113: H.A. Casita de los Abuelos | C113: H.A. Casita de los Abuelos | D113: Calle Guzmán S/N Ituzaingó | E113: 3786-457697 (Tomasa Gauto) | F113: Dto. de Ituzaingó | G113: Ituzaingó | H113: 45 | I113: MIN. Y FLIA. | J113: COMIDAS
A114: C | B114: H.A. Casita de los Abuelos | C114: H.A. Casita de los Abuelos | D114: Calle Guzmán S/N Ituzaingó | E114: 3786-457697 (Tomasa Gauto) | F114: Dto. de Ituzaingó | G114: Ituzaingó | H114: 50 | I114: MIN. Y FLIA. | J114: REFRIGERIOS
A115: C | B115: Isla Apipé Grande San Antonio | C115: Isla Apipé Grande San Antonio | D115: Isla Apipé Gde. San Antonio | E115: 3786-618213-Dolores Toledo | F115: Dto. de Ituzaingó | G115: Ituzaingó | H115: 100 | I115: ACCION SOCIAL | J115: COMIDAS
A116: C | B116: Isla Apipé Grande San Antonio | C116: Isla Apipé Grande San Antonio | D116: Isla Apipé Gde. San Antonio | E116: 3786-618213-Dolores Toledo | F116: Dto. de Ituzaingó | G116: Ituzaingó | H116: 15 | I116: ACCION SOCIAL | J116: REFRIGERIOS
A117: C | B117: Liga Ituzaingueña de Fútbol (para 6 clubes) | C117: Liga Ituzaingueña de Fútbol (para 6 clubes) | D117: ITUZAINGÓ CTES. | E117: 3786 40-3346 Walter Gómez | F117: Dto. de Ituzaingó | G117: Ituzaingó | H117: 150 | I117: ACCION SOCIAL | J117: REFRIGERIOS
A118: C | B118: C.P.M. Nº 21 "Mita Ñangareko - Ha" | C118: C.P.M. Nº 21 "Mita Ñangareko - Ha" | D118: Ruta N°12 Villa Olivari - Ituzaingó | E118: 3786-401215 (Paola salinas) | F118: Dto. de Ituzaingó | G118: Villa Olivari | H118: 70 | I118: MIN. Y FLIA. | J118: COMIDAS
A119: C | B119: C.P.M. Nº 21 "Mita Ñangareko - Ha" | C119: C.P.M. Nº 21 "Mita Ñangareko - Ha" | D119: Ruta N°12 Villa Olivari - Ituzaingó | E119: 3786-401215 (Paola salinas) | F119: Dto. de Ituzaingó | G119: Villa Olivari | H119: 70 | I119: MIN. Y FLIA. | J119: REFRIGERIOS
...

Sheet PRESUPUESTO
B2: RAC. DÍA
B3: COMIDA | C3: REFRIGERIOS | I3: COBERTURA
B4: 29226 | C4: 33838 | J4: CANT. DÍAS
I5: PLAN VERANO | J5: 42
I6: PALN 1 | J6: 30
B7: PRECIO UNITARIO POR RAC. | I7: PLAN 2 | J7: 30
B8: 1600 | I8: PLAN 3 | J8: 30
I9: PLAN 4 | J9: 30
B10: PRESUPUESTO DIARIO | I10: PLAN 5 | J10: 30
B11: =B4*B8 -> 46761600 | C11: =C4*B8 -> 54140800 | I11: PLAN 6 | J11: 30
B12: TOTAL DIARIO | I12: PLAN 7 | J12: 30
B13: =SUM(B11+C11) -> 100902400 | I13: TOTAL
I14: DÍAS | J14: =SUM(J5:J12) -> 252
B15: TOTAL 30 DIAS
B16: =SUM(B13*30) -> 3027072000
B18: TOTAL 252 DÍAS (ANUAL)
B19: =SUM(B13*252) -> 25427404800
